applications/__init__.py
applications/emotic_resnet50.py
applications/emotic_utils.py
applications/emotic_vgg16.py
applications/emotic_vgg19.py
applications/hra_resnet50.py
applications/hra_utils.py
applications/hra_vgg16.py
applications/hra_vgg16_places365.py
applications/hra_vgg19.py
applications/vgg16_places_365.py
datasets/__init__.py
engine/__init__.py
engine/displaced_people_branch/__init__.py
engine/displaced_people_branch/single_image_inference_hra_2class.py
engine/human_centric_branch/__init__.py
engine/human_centric_branch/emotic_vad_model.py
engine/human_centric_branch/global_emotional_traits_branch.py
engine/object_detection_branch/__init__.py
engine/object_detection_branch/ssd_detector.py
engine/object_detection_branch/retina_net/__init__.py
engine/object_detection_branch/retina_net/setup.py
engine/object_detection_branch/retina_net/single_img_inference.py
engine/object_detection_branch/retina_net/examples/ResNet50RetinaNet.py
engine/object_detection_branch/retina_net/examples/__init__.py
engine/object_detection_branch/retina_net/keras_retinanet/__init__.py
engine/object_detection_branch/retina_net/keras_retinanet/initializers.py
engine/object_detection_branch/retina_net/keras_retinanet/losses.py
engine/object_detection_branch/retina_net/keras_retinanet/backend/__init__.py
engine/object_detection_branch/retina_net/keras_retinanet/backend/cntk_backend.py
engine/object_detection_branch/retina_net/keras_retinanet/backend/common.py
engine/object_detection_branch/retina_net/keras_retinanet/backend/dynamic.py
engine/object_detection_branch/retina_net/keras_retinanet/backend/tensorflow_backend.py
engine/object_detection_branch/retina_net/keras_retinanet/backend/theano_backend.py
engine/object_detection_branch/retina_net/keras_retinanet/bin/__init__.py
engine/object_detection_branch/retina_net/keras_retinanet/bin/convert_model.py
engine/object_detection_branch/retina_net/keras_retinanet/bin/debug.py
DisplaceNet-0.1.dist-info/LICENSE
DisplaceNet-0.1.dist-info/METADATA
DisplaceNet-0.1.dist-info/WHEEL
DisplaceNet-0.1.dist-info/top_level.txt
DisplaceNet-0.1.dist-info/RECORD
