Metadata-Version: 2.1
Name: DisplaceNet
Version: 0.1
Summary: Recognising Displaced People from Images by Exploiting Dominance Level
Home-page: https://github.com/GKalliatakis/DisplaceNet
Author: Grigorios Kalliatakis
Author-email: gkallia@essex.ac.uk
License: MIT
Download-URL: https://github.com/GKalliatakis/DisplaceNet/archive/master.zip
Platform: UNKNOWN
Classifier: Programming Language :: Python :: 2.7
Classifier: Programming Language :: Python :: 3
Classifier: Programming Language :: Python :: 3.6
Classifier: License :: OSI Approved :: MIT License
Classifier: Operating System :: OS Independent
Classifier: Intended Audience :: Developers
Classifier: Intended Audience :: Education
Classifier: Intended Audience :: Science/Research
